{
  "resource": "Posts",
  "http_method": "GET",
  "route": "/api/v1/posts/recent",
  "description": "Listing all recent posts",
  "explanation": null,
  "parameters": [

  ],
  "requests": [
    {
      "request_method": "GET",
      "request_path": "/api/v1/posts/recent",
      "request_body": null,
      "request_headers": {
        "Content-Type": "application/json",
        "Host": "example.org",
        "Cookie": ""
      },
      "request_query_parameters": {
      },
      "request_content_type": "application/json",
      "response_status": 200,
      "response_status_text": "OK",
      "response_body": "[{\"id\":351,\"text\":\"its a #test post 2.0 3\",\"score\":null,\"created_at\":\"2014-06-30T06:41:46.503Z\",\"updated_at\":\"2014-06-30T06:41:46.503Z\",\"college_id\":2016,\"lat\":null,\"lon\":null},{\"id\":350,\"text\":\"its a #test post 2.0 2\",\"score\":null,\"created_at\":\"2014-06-30T06:41:46.495Z\",\"updated_at\":\"2014-06-30T06:41:46.495Z\",\"college_id\":2016,\"lat\":null,\"lon\":null},{\"id\":349,\"text\":\"its a #test post 2.0 1\",\"score\":null,\"created_at\":\"2014-06-30T06:41:46.481Z\",\"updated_at\":\"2014-06-30T06:41:46.481Z\",\"college_id\":2016,\"lat\":null,\"lon\":null},{\"id\":348,\"text\":\"its a #test post 3\",\"score\":null,\"created_at\":\"2014-06-30T06:41:46.470Z\",\"updated_at\":\"2014-06-30T06:41:46.470Z\",\"college_id\":2015,\"lat\":null,\"lon\":null},{\"id\":347,\"text\":\"its a #test post 2\",\"score\":null,\"created_at\":\"2014-06-30T06:41:46.461Z\",\"updated_at\":\"2014-06-30T06:41:46.461Z\",\"college_id\":2015,\"lat\":null,\"lon\":null},{\"id\":346,\"text\":\"its a #test post 1\",\"score\":null,\"created_at\":\"2014-06-30T06:41:46.453Z\",\"updated_at\":\"2014-06-30T06:41:46.453Z\",\"college_id\":2015,\"lat\":null,\"lon\":null}]",
      "response_headers": {"X-Frame-Options":"SAMEORIGIN","X-XSS-Protection":"1; mode=block","X-Content-Type-Options":"nosniff","X-UA-Compatible":"chrome=1","Content-Type":"application/json; charset=utf-8","ETag":"\"75e75552a317740b24d180852084f3d0\"","Cache-Control":"max-age=0, private, must-revalidate","Set-Cookie":"request_method=GET; path=/","X-Request-Id":"ce780020-b5d1-47cc-ba97-a9957bd55536","X-Runtime":"0.042029","Content-Length":"1045"},
      "response_content_type": "application/json; charset=utf-8",
      "curl": null
}
  ]
}