{
  "resource": "Comments",
  "http_method": "POST",
  "route": "/api/v1/posts/1/comments",
  "description": "Creating a comment for a given post",
  "explanation": null,
  "parameters": [
    {
      "required": true,
      "name": "comment",
      "description": "The new comment."
    }
  ],
  "requests": [
    {
      "request_method": "POST",
      "request_path": "/api/v1/posts/1/comments",
      "request_body": "{\"text\":\"This is my comment on post id 1\"}",
      "request_headers": {
        "Content-Type": "application/json",
        "Host": "example.org",
        "Cookie": ""
      },
      "request_query_parameters": {
      },
      "request_content_type": "application/json",
      "response_status": 201,
      "response_status_text": "Created",
      "response_body": "{\"id\":13,\"text\":\"This is my comment on post id 1\",\"score\":null,\"post_id\":1,\"created_at\":\"2014-06-29T07:21:25.331Z\",\"updated_at\":\"2014-06-29T07:21:25.331Z\"}",
      "response_headers": {"X-Frame-Options":"SAMEORIGIN","X-XSS-Protection":"1; mode=block","X-Content-Type-Options":"nosniff","X-UA-Compatible":"chrome=1","Location":"http://example.org/api/v1/comments/13","Content-Type":"application/json; charset=utf-8","ETag":"\"05e330216d3fec5f09e51ea33a37e1b3\"","Cache-Control":"max-age=0, private, must-revalidate","Set-Cookie":"request_method=POST; path=/","X-Request-Id":"dc3d056f-79ae-4362-9c75-76cf461bb557","X-Runtime":"0.082055","Content-Length":"155"},
      "response_content_type": "application/json; charset=utf-8",
      "curl": null
}
  ]
}