{
  "resource": "Votes",
  "http_method": "POST",
  "route": "/api/v1/posts/101/votes",
  "description": "Casting a vote on post ID 101",
  "explanation": null,
  "parameters": [
    {
      "required": true,
      "name": "upvote",
      "description": "The new vote's upvote or downvote status."
    }
  ],
  "requests": [
    {
      "request_method": "POST",
      "request_path": "/api/v1/posts/101/votes",
      "request_body": "{\"upvote\":true}",
      "request_headers": {
        "Content-Type": "application/json",
        "Host": "example.org",
        "Cookie": ""
      },
      "request_query_parameters": {
      },
      "request_content_type": "application/json",
      "response_status": 201,
      "response_status_text": "Created",
      "response_body": "{\"id\":102,\"upvote\":true,\"votable_id\":101,\"votable_type\":\"Post\",\"created_at\":\"2014-07-29T06:45:04.234Z\",\"updated_at\":\"2014-07-29T06:45:04.234Z\"}",
      "response_headers": {"X-Frame-Options":"SAMEORIGIN","X-XSS-Protection":"1; mode=block","X-Content-Type-Options":"nosniff","X-UA-Compatible":"chrome=1","Content-Type":"application/json; charset=utf-8","ETag":"\"e545fd81de25694da03153af53994df7\"","Cache-Control":"max-age=0, private, must-revalidate","Set-Cookie":"request_method=POST; path=/","X-Request-Id":"a919df89-f466-4e9b-b89e-deb463d1edf4","X-Runtime":"0.006921","Content-Length":"143"},
      "response_content_type": "application/json; charset=utf-8",
      "curl": null
}
  ]
}